<?xml version="1.0" encoding="utf-8" ?>
<dwsync>
<file name="icon_bosspepper.gif" server="192.168.0.201/hot7/" local="132158745870557832" remote="131419296000000000" Dst="0" />
<file name="icon_cookbeef.gif" server="192.168.0.201/hot7/" local="132158745872617832" remote="131304384000000000" Dst="0" />
<file name="icon_12sabu.gif" server="192.168.0.201/hot7/" local="132158745872637832" remote="131224896000000000" Dst="0" />
<file name="icon_giguo.gif" server="192.168.0.201/hot7/" local="132158745872677832" remote="131788224000000000" Dst="0" />
<file name="icon_gun8.gif" server="192.168.0.201/hot7/" local="132158745872837832" remote="131341536000000000" Dst="0" />
<file name="icon_hot7.gif" server="192.168.0.201/hot7/" local="132158745872867832" remote="131224896000000000" Dst="0" />
<file name="icon_ilamu.gif" server="192.168.0.201/hot7/" local="132158745873077832" remote="131224896000000000" Dst="0" />
<file name="icon_ita.gif" server="192.168.0.201/hot7/" local="132158745873107832" remote="131245632000000000" Dst="0" />
<file name="icon_ikki.gif" server="192.168.0.201/hot7/" local="132158745874847832" remote="131224896000000000" Dst="0" />
<file name="icon_putien.gif" server="192.168.0.201/hot7/" local="132158745875287832" remote="131225760000000000" Dst="0" />
<file name="icon_lady.jpg" server="192.168.0.201/hot7/" local="132158745875437832" remote="131341536000000000" Dst="0" />
<file name="icon_PT.gif" server="192.168.0.201/hot7/" local="132158745875477832" remote="131245632000000000" Dst="0" />
<file name="icon_s3.gif" server="192.168.0.201/hot7/" local="132158745875667832" remote="131398560000000000" Dst="0" />
<file name="icon_taoban.jpg" server="192.168.0.201/hot7/" local="132158745875867832" remote="131224896000000000" Dst="0" />
<file name="icon_sufood.gif" server="192.168.0.201/hot7/" local="132158745877647832" remote="131919920400000000" Dst="0" />
<file name="icon_tasty.gif" server="192.168.0.201/hot7/" local="132158745877967832" remote="131224896000000000" Dst="0" />
<file name="icon_wowprime.gif" server="192.168.0.201/hot7/" local="132158745878027832" remote="131224896000000000" Dst="0" />
<file name="icon_wangsteak.gif" server="192.168.0.201/hot7/" local="132158745878067832" remote="131224896000000000" Dst="0" />
<file name="icon_xiamuni.gif" server="192.168.0.201/hot7/" local="132158745880117832" remote="131224896000000000" Dst="0" />
<file name="icon_yuan.gif" server="192.168.0.201/hot7/" local="132158745880177832" remote="131224896000000000" Dst="0" />
<file name="icon_zen - 複製.gif" server="192.168.0.201/hot7/" local="132158745880227832" remote="131224896000000000" Dst="0" />
<file name="Thumbs.db" server="192.168.0.201/hot7/" local="132158745880387832" remote="131225760000000000" Dst="0" />
<file name="icon_zen.gif" server="192.168.0.201/hot7/" local="132158745882277832" remote="131225760000000000" Dst="0" />
</dwsync>