<?xml version="1.0" encoding="utf-8" ?>
<dwsync>
<file name="branches_E.htm" server="192.168.0.201/ikki/" local="132158638700869124" remote="130455072000000000" Dst="0" />
<file name="branches_E1122.htm" server="192.168.0.201/ikki/" local="132158638701119149" remote="130455072000000000" Dst="0" />
<file name="branches_E1218.htm" server="192.168.0.201/ikki/" local="132158638703399377" remote="130455072000000000" Dst="0" />
<file name="index.htm" server="192.168.0.201/ikki/" local="132158638731232160" remote="130455072000000000" Dst="0" />
<file name="menu_E0501.htm" server="192.168.0.201/ikki/" local="132158638731612198" remote="130455072000000000" Dst="0" />
<file name="menu_E.htm" server="192.168.0.201/ikki/" local="132158638733342371" remote="130455072000000000" Dst="0" />
<file name="menu_E0428.htm" server="192.168.0.201/ikki/" local="132158638733502387" remote="130455072000000000" Dst="0" />
<file name="menu_E0805.htm" server="192.168.0.201/ikki/" local="132158638735312568" remote="130455072000000000" Dst="0" />
<file name="menu_E1017.htm" server="192.168.0.201/ikki/" local="132158638735522589" remote="130455072000000000" Dst="0" />
<file name="menu_E_v.htm" server="192.168.0.201/ikki/" local="132158638735772614" remote="130455072000000000" Dst="0" />
<file name="menu_E_v1017.htm" server="192.168.0.201/ikki/" local="132158638737552792" remote="130455072000000000" Dst="0" />
<file name="menu_J0428.htm" server="192.168.0.201/ikki/" local="132158638737592796" remote="130455072000000000" Dst="0" />
<file name="menu_J.htm" server="192.168.0.201/ikki/" local="132158638737702807" remote="130455072000000000" Dst="0" />
<file name="menu_J0501htm" server="192.168.0.201/ikki/" local="132158638737792816" remote="130455072000000000" Dst="0" />
<file name="menu_J0805.htm" server="192.168.0.201/ikki/" local="132158638737832820" remote="130455072000000000" Dst="0" />
<file name="menu_J1017.htm" server="192.168.0.201/ikki/" local="132158638739983035" remote="130455072000000000" Dst="0" />
<file name="menu_J_v1017.htm" server="192.168.0.201/ikki/" local="132158638740023039" remote="130455072000000000" Dst="0" />
<file name="menu_J_v.htm" server="192.168.0.201/ikki/" local="132158638740073044" remote="130455072000000000" Dst="0" />
</dwsync>