<?xml version="1.0" encoding="utf-8" ?>
<dwsync>
<file name="1505754adc60000003e4.JPG" server="192.168.0.201/wangsteak/" local="132157832908761210" remote="132130655400000000" Dst="0" />
<file name="16_ftt.gif" server="192.168.0.201/wangsteak/" local="132157832909311265" remote="132130655400000000" Dst="0" />
<file name="18_strawberry.jpg" server="192.168.0.201/wangsteak/" local="132157832909321266" remote="132130655400000000" Dst="0" />
<file name="16_food.gif" server="192.168.0.201/wangsteak/" local="132157832911281462" remote="132130655400000000" Dst="0" />
<file name="about-banner.jpg" server="192.168.0.201/wangsteak/" local="132157832911591493" remote="132130655400000000" Dst="0" />
<file name="404-banner.gif" server="192.168.0.201/wangsteak/" local="132157832911651499" remote="132130655400000000" Dst="0" />
<file name="about-box1-bg.jpg" server="192.168.0.201/wangsteak/" local="132157832911691503" remote="132130655400000000" Dst="0" />
<file name="about2-box1-bg.jpg" server="192.168.0.201/wangsteak/" local="132157832911791513" remote="132130655400000000" Dst="0" />
<file name="about2-box1-img.png" server="192.168.0.201/wangsteak/" local="132157832912201554" remote="132130655400000000" Dst="0" />
<file name="about2-box2-list (1).jpg" server="192.168.0.201/wangsteak/" local="132157832912661600" remote="132130655400000000" Dst="0" />
<file name="about-box2.png" server="192.168.0.201/wangsteak/" local="132157832914151749" remote="132130655400000000" Dst="0" />
<file name="about2-box1-img2.png" server="192.168.0.201/wangsteak/" local="132157832914361770" remote="132130655400000000" Dst="0" />
<file name="about2-box2-list (2).jpg" server="192.168.0.201/wangsteak/" local="132157832916011935" remote="132130655400000000" Dst="0" />
<file name="about2-box2-list (5).jpg" server="192.168.0.201/wangsteak/" local="132157832916511985" remote="132130655400000000" Dst="0" />
<file name="about2-box2-list (4).jpg" server="192.168.0.201/wangsteak/" local="132157832916531987" remote="132130655400000000" Dst="0" />
<file name="about2-box2-list (3).jpg" server="192.168.0.201/wangsteak/" local="132157832916662000" remote="132130655400000000" Dst="0" />
<file name="about2-box2-list (6).jpg" server="192.168.0.201/wangsteak/" local="132157832916782012" remote="132130655400000000" Dst="0" />
<file name="about2-box2-list (8).jpg" server="192.168.0.201/wangsteak/" local="132157832918812215" remote="132130655400000000" Dst="0" />
<file name="about2-box2-list (7).jpg" server="192.168.0.201/wangsteak/" local="132157832918872221" remote="132130655400000000" Dst="0" />
<file name="about2-box2-list (9).jpg" server="192.168.0.201/wangsteak/" local="132157832918942228" remote="132130655400000000" Dst="0" />
<file name="about2-box2.jpg" server="192.168.0.201/wangsteak/" local="132157832919042238" remote="132130655400000000" Dst="0" />
<file name="about2-box3-01.jpg" server="192.168.0.201/wangsteak/" local="132157832919082242" remote="132130655400000000" Dst="0" />
<file name="about2-box3-02.jpg" server="192.168.0.201/wangsteak/" local="132157832919232257" remote="132130655400000000" Dst="0" />
<file name="about2-box3-03.jpg" server="192.168.0.201/wangsteak/" local="132157832919392273" remote="132130655400000000" Dst="0" />
<file name="about2-box3-05.jpg" server="192.168.0.201/wangsteak/" local="132157832919562290" remote="132130655400000000" Dst="0" />
<file name="about2-box3-06.jpg" server="192.168.0.201/wangsteak/" local="132157832919632297" remote="132130655400000000" Dst="0" />
<file name="about2-box3-08.jpg" server="192.168.0.201/wangsteak/" local="132157832919872321" remote="132130655400000000" Dst="0" />
<file name="about2-box3-09.jpg" server="192.168.0.201/wangsteak/" local="132157832921272461" remote="132130655400000000" Dst="0" />
<file name="about2-box3-04.jpg" server="192.168.0.201/wangsteak/" local="132157832921442478" remote="132130655400000000" Dst="0" />
<file name="about3-box1-mv.jpg" server="192.168.0.201/wangsteak/" local="132157832921672501" remote="132130655400000000" Dst="0" />
<file name="about2-box3-07.jpg" server="192.168.0.201/wangsteak/" local="132157832921762510" remote="132130655400000000" Dst="0" />
<file name="about3-box1-mv1.jpg" server="192.168.0.201/wangsteak/" local="132157832922072541" remote="132130655400000000" Dst="0" />
<file name="about2-box3.jpg" server="192.168.0.201/wangsteak/" local="132157832923662700" remote="132130655400000000" Dst="0" />
<file name="about3-box2-01-1.jpg" server="192.168.0.201/wangsteak/" local="132157832923672701" remote="132130655400000000" Dst="0" />
<file name="about3-box2-01-2.jpg" server="192.168.0.201/wangsteak/" local="132157832923972731" remote="132130655400000000" Dst="0" />
<file name="about3-box1.jpg" server="192.168.0.201/wangsteak/" local="132157832924022736" remote="132130655400000000" Dst="0" />
<file name="about3-box2-01-3.jpg" server="192.168.0.201/wangsteak/" local="132157832924092743" remote="132130655400000000" Dst="0" />
<file name="about3-box2-01-4.jpg" server="192.168.0.201/wangsteak/" local="132157832924302764" remote="132130655400000000" Dst="0" />
<file name="about3-box2-01.jpg" server="192.168.0.201/wangsteak/" local="132157832924332767" remote="132130655400000000" Dst="0" />
<file name="about3-box2-02-1.jpg" server="192.168.0.201/wangsteak/" local="132157832924362770" remote="132130655400000000" Dst="0" />
<file name="about3-box2-02-4.jpg" server="192.168.0.201/wangsteak/" local="132157832924622796" remote="132130655400000000" Dst="0" />
<file name="about3-box2-02-2.jpg" server="192.168.0.201/wangsteak/" local="132157832926542988" remote="132130655400000000" Dst="0" />
<file name="about3-box2-02-3.jpg" server="192.168.0.201/wangsteak/" local="132157832926572991" remote="132130655400000000" Dst="0" />
<file name="about3-box2-03-2.jpg" server="192.168.0.201/wangsteak/" local="132157832926763010" remote="132130655400000000" Dst="0" />
<file name="about3-box2-02.jpg" server="192.168.0.201/wangsteak/" local="132157832928583192" remote="132130655400000000" Dst="0" />
<file name="about3-box2-03-1.jpg" server="192.168.0.201/wangsteak/" local="132157832928703204" remote="132130655400000000" Dst="0" />
<file name="about3-box2-03-3.jpg" server="192.168.0.201/wangsteak/" local="132157832928893223" remote="132130655400000000" Dst="0" />
<file name="about3-box2-03.jpg" server="192.168.0.201/wangsteak/" local="132157832929123246" remote="132130655400000000" Dst="0" />
<file name="about3-box2-04-1.jpg" server="192.168.0.201/wangsteak/" local="132157832929173251" remote="132130655400000000" Dst="0" />
<file name="about3-box2-03-4.jpg" server="192.168.0.201/wangsteak/" local="132157832930933427" remote="132130655400000000" Dst="0" />
<file name="about3-box2-04-3.jpg" server="192.168.0.201/wangsteak/" local="132157832931423476" remote="132130655400000000" Dst="0" />
<file name="about3-box2-04-2.jpg" server="192.168.0.201/wangsteak/" local="132157832931483482" remote="132130655400000000" Dst="0" />
<file name="about3-box2-05-1.jpg" server="192.168.0.201/wangsteak/" local="132157832931723506" remote="132130655400000000" Dst="0" />
<file name="about3-box2-04.jpg" server="192.168.0.201/wangsteak/" local="132157832931743508" remote="132130655400000000" Dst="0" />
<file name="about3-box2-04-4.jpg" server="192.168.0.201/wangsteak/" local="132157832933313665" remote="132130655400000000" Dst="0" />
<file name="about3-box2-05-2.jpg" server="192.168.0.201/wangsteak/" local="132157832933983732" remote="132130655400000000" Dst="0" />
<file name="about3-box2-05-3.jpg" server="192.168.0.201/wangsteak/" local="132157832934013735" remote="132130655400000000" Dst="0" />
<file name="about3-box2-05-4.jpg" server="192.168.0.201/wangsteak/" local="132157832934043738" remote="132130655400000000" Dst="0" />
<file name="about3-box2-05.jpg" server="192.168.0.201/wangsteak/" local="132157832936253959" remote="132130655400000000" Dst="0" />
<file name="about3-box2-bg.jpg" server="192.168.0.201/wangsteak/" local="132157832936283962" remote="132130655400000000" Dst="0" />
<file name="about3-list01.jpg" server="192.168.0.201/wangsteak/" local="132157832936433977" remote="132130655400000000" Dst="0" />
<file name="about4-box-icon1.png" server="192.168.0.201/wangsteak/" local="132157832938474181" remote="132130655400000000" Dst="0" />
<file name="about4-box-icon2.png" server="192.168.0.201/wangsteak/" local="132157832938524186" remote="132130655400000000" Dst="0" />
<file name="about_03.jpg" server="192.168.0.201/wangsteak/" local="132157832938694203" remote="132130655400000000" Dst="0" />
<file name="about_box2.jpg" server="192.168.0.201/wangsteak/" local="132157832938924226" remote="132130655400000000" Dst="0" />
<file name="banner-logo.png" server="192.168.0.201/wangsteak/" local="132157832939144248" remote="132130655400000000" Dst="0" />
<file name="about4-box1.png" server="192.168.0.201/wangsteak/" local="132157832939694303" remote="132130655400000000" Dst="0" />
<file name="app.png" server="192.168.0.201/wangsteak/" local="132157832941014435" remote="132130655400000000" Dst="0" />
<file name="bg.gif" server="192.168.0.201/wangsteak/" local="132157832942034537" remote="132130655400000000" Dst="0" />
<file name="banner.jpg" server="192.168.0.201/wangsteak/" local="132157832942044538" remote="132130655400000000" Dst="0" />
<file name="bg2.gif" server="192.168.0.201/wangsteak/" local="132157832943744708" remote="132130655400000000" Dst="0" />
<file name="ch.png" server="192.168.0.201/wangsteak/" local="132157832944154749" remote="132130655400000000" Dst="0" />
<file name="bg3.gif" server="192.168.0.201/wangsteak/" local="132157832944184752" remote="132130655400000000" Dst="0" />
<file name="ch_03.gif" server="192.168.0.201/wangsteak/" local="132157832944354769" remote="132130655400000000" Dst="0" />
<file name="code.png" server="192.168.0.201/wangsteak/" local="132157832946404974" remote="132130655400000000" Dst="0" />
<file name="conpon-bg.jpg" server="192.168.0.201/wangsteak/" local="132157832946534987" remote="132130655400000000" Dst="0" />
<file name="conpon-birthday.jpg" server="192.168.0.201/wangsteak/" local="132157832946544988" remote="132130655400000000" Dst="0" />
<file name="contant-icon.png" server="192.168.0.201/wangsteak/" local="132157832946685002" remote="132130655400000000" Dst="0" />
<file name="contact-banner.jpg" server="192.168.0.201/wangsteak/" local="132157832946745008" remote="132130655400000000" Dst="0" />
<file name="event-img.png" server="192.168.0.201/wangsteak/" local="132157832946975031" remote="132130655400000000" Dst="0" />
<file name="conpon-marry.jpg" server="192.168.0.201/wangsteak/" local="132157832948695203" remote="132130655400000000" Dst="0" />
<file name="events-banner.jpg" server="192.168.0.201/wangsteak/" local="132157832948715205" remote="132130655400000000" Dst="0" />
<file name="event-img.jpg" server="192.168.0.201/wangsteak/" local="132157832948925226" remote="132130655400000000" Dst="0" />
<file name="events-pic1_07.jpg" server="192.168.0.201/wangsteak/" local="132157832949185252" remote="132130655400000000" Dst="0" />
<file name="events-pic1_04.jpg" server="192.168.0.201/wangsteak/" local="132157832949215255" remote="132130655400000000" Dst="0" />
<file name="events-pic1_10.jpg" server="192.168.0.201/wangsteak/" local="132157832949455279" remote="132130655400000000" Dst="0" />
<file name="events-pic1_12.jpg" server="192.168.0.201/wangsteak/" local="132157832949495283" remote="132130655400000000" Dst="0" />
<file name="events-pic1_25th.jpg" server="192.168.0.201/wangsteak/" local="132157832949675301" remote="132130655400000000" Dst="0" />
<file name="events-pic1_15.jpg" server="192.168.0.201/wangsteak/" local="132157832949755309" remote="132130655400000000" Dst="0" />
<file name="food-banner.jpg" server="192.168.0.201/wangsteak/" local="132157832949885322" remote="132130655400000000" Dst="0" />
<file name="food-icon1.png" server="192.168.0.201/wangsteak/" local="132157832949915325" remote="132130655400000000" Dst="0" />
<file name="food-icon2.png" server="192.168.0.201/wangsteak/" local="132157832950035337" remote="132130655400000000" Dst="0" />
<file name="events-pic1_02.jpg" server="192.168.0.201/wangsteak/" local="132157832951165450" remote="132130655400000000" Dst="0" />
<file name="food_c_03.jpg" server="192.168.0.201/wangsteak/" local="132157832952165550" remote="132130655400000000" Dst="0" />
<file name="footer-bg.jpg" server="192.168.0.201/wangsteak/" local="132157832952285562" remote="132130655400000000" Dst="0" />
<file name="home-activity-01.jpg" server="192.168.0.201/wangsteak/" local="132157832952455579" remote="132130655400000000" Dst="0" />
<file name="home-activity-02.jpg" server="192.168.0.201/wangsteak/" local="132157832952475581" remote="132130655400000000" Dst="0" />
<file name="home-activity-04.jpg" server="192.168.0.201/wangsteak/" local="132157832952755609" remote="132130655400000000" Dst="0" />
<file name="footer-bg.png" server="192.168.0.201/wangsteak/" local="132157832954155749" remote="132130655400000000" Dst="0" />
<file name="home-activity-03.jpg" server="192.168.0.201/wangsteak/" local="132157832954755809" remote="132130655400000000" Dst="0" />
<file name="home-activity.jpg" server="192.168.0.201/wangsteak/" local="132157832956355969" remote="132130655400000000" Dst="0" />
<file name="home-exclusive-pic01.jpg" server="192.168.0.201/wangsteak/" local="132157832956555989" remote="132130655400000000" Dst="0" />
<file name="home-member-01_1.jpg" server="192.168.0.201/wangsteak/" local="132157832956706004" remote="132130655400000000" Dst="0" />
<file name="home-member-01_2.jpg" server="192.168.0.201/wangsteak/" local="132157832956726006" remote="132130655400000000" Dst="0" />
<file name="home-member-02_1.jpg" server="192.168.0.201/wangsteak/" local="132157832956906024" remote="132130655400000000" Dst="0" />
<file name="home-member-02_2.jpg" server="192.168.0.201/wangsteak/" local="132157832958116145" remote="132130655400000000" Dst="0" />
<file name="home-member-01.jpg" server="192.168.0.201/wangsteak/" local="132157832958266160" remote="132130655400000000" Dst="0" />
<file name="home-menu-pic01.jpg" server="192.168.0.201/wangsteak/" local="132157832958486182" remote="132130655400000000" Dst="0" />
<file name="home-member-02.jpg" server="192.168.0.201/wangsteak/" local="132157832958966230" remote="132130655400000000" Dst="0" />
<file name="home-menu-pic02.jpg" server="192.168.0.201/wangsteak/" local="132157832960416375" remote="132130655400000000" Dst="0" />
<file name="icon_bosspepper.gif" server="192.168.0.201/wangsteak/" local="132157832960546388" remote="132130655400000000" Dst="0" />
<file name="home-menu-pic03.jpg" server="192.168.0.201/wangsteak/" local="132157832960956429" remote="132130655400000000" Dst="0" />
<file name="icon_cookbeef.gif" server="192.168.0.201/wangsteak/" local="132157832961436477" remote="132130655400000000" Dst="0" />
<file name="icon_gun8.gif" server="192.168.0.201/wangsteak/" local="132157832961556489" remote="132130655400000000" Dst="0" />
<file name="icon_hot7.gif" server="192.168.0.201/wangsteak/" local="132157832961676501" remote="132130655400000000" Dst="0" />
<file name="icon_12sabu.gif" server="192.168.0.201/wangsteak/" local="132157832962476581" remote="132130655400000000" Dst="0" />
<file name="icon_giguo.gif" server="192.168.0.201/wangsteak/" local="132157832963566690" remote="132130655400000000" Dst="0" />
<file name="icon_ikki.gif" server="192.168.0.201/wangsteak/" local="132157832964556789" remote="132130655400000000" Dst="0" />
<file name="icon_ita.gif" server="192.168.0.201/wangsteak/" local="132157832964606794" remote="132130655400000000" Dst="0" />
<file name="icon_ilamu.gif" server="192.168.0.201/wangsteak/" local="132157832964626796" remote="132130655400000000" Dst="0" />
<file name="icon_lady.jpg" server="192.168.0.201/wangsteak/" local="132157832966707004" remote="132130655400000000" Dst="0" />
<file name="icon_PT.gif" server="192.168.0.201/wangsteak/" local="132157832966767010" remote="132130655400000000" Dst="0" />
<file name="icon_putien.gif" server="192.168.0.201/wangsteak/" local="132157832966777011" remote="132130655400000000" Dst="0" />
<file name="icon_sufood.gif" server="192.168.0.201/wangsteak/" local="132157832966907024" remote="132130655400000000" Dst="0" />
<file name="icon_taoban.gif" server="192.168.0.201/wangsteak/" local="132157832968897223" remote="132130655400000000" Dst="0" />
<file name="icon_tasty.gif" server="192.168.0.201/wangsteak/" local="132157832968937227" remote="132130655400000000" Dst="0" />
<file name="icon_wangsteak.gif" server="192.168.0.201/wangsteak/" local="132157832969077241" remote="132130655400000000" Dst="0" />
<file name="icon_wowprime.gif" server="192.168.0.201/wangsteak/" local="132157832969107244" remote="132130655400000000" Dst="0" />
<file name="icon_xiamuni.gif" server="192.168.0.201/wangsteak/" local="132157832971107444" remote="132130655400000000" Dst="0" />
<file name="icon_yuan.gif" server="192.168.0.201/wangsteak/" local="132157832971337467" remote="132130655400000000" Dst="0" />
<file name="icon_zen.gif" server="192.168.0.201/wangsteak/" local="132157832971357469" remote="132130655400000000" Dst="0" />
<file name="icon_zhabeef.gif" server="192.168.0.201/wangsteak/" local="132157832971377471" remote="132130655400000000" Dst="0" />
<file name="link-banner.jpg" server="192.168.0.201/wangsteak/" local="132157832971637497" remote="132130655400000000" Dst="0" />
<file name="link-icon.png" server="192.168.0.201/wangsteak/" local="132157832972027536" remote="132130655400000000" Dst="0" />
<file name="links_03.jpg" server="192.168.0.201/wangsteak/" local="132157832972247558" remote="132130655400000000" Dst="0" />
<file name="Image 001.png" server="192.168.0.201/wangsteak/" local="132157832974177751" remote="132130655400000000" Dst="0" />
<file name="links_05.jpg" server="192.168.0.201/wangsteak/" local="132157832974417775" remote="132130655400000000" Dst="0" />
<file name="Image 002.png" server="192.168.0.201/wangsteak/" local="132157832974477781" remote="132130655400000000" Dst="0" />
<file name="links_09.jpg" server="192.168.0.201/wangsteak/" local="132157832974627796" remote="132130655400000000" Dst="0" />
<file name="links_11.jpg" server="192.168.0.201/wangsteak/" local="132157832974717805" remote="132130655400000000" Dst="0" />
<file name="links_18.jpg" server="192.168.0.201/wangsteak/" local="132157832974807814" remote="132130655400000000" Dst="0" />
<file name="links_19.jpg" server="192.168.0.201/wangsteak/" local="132157832974877821" remote="132130655400000000" Dst="0" />
<file name="links_20.jpg" server="192.168.0.201/wangsteak/" local="132157832974967830" remote="132130655400000000" Dst="0" />
<file name="links_07.jpg" server="192.168.0.201/wangsteak/" local="132157832976477981" remote="132130655400000000" Dst="0" />
<file name="links_22.jpg" server="192.168.0.201/wangsteak/" local="132157832977038037" remote="132130655400000000" Dst="0" />
<file name="links_31.jpg" server="192.168.0.201/wangsteak/" local="132157832977058039" remote="132130655400000000" Dst="0" />
<file name="links_24.jpg" server="192.168.0.201/wangsteak/" local="132157832977188052" remote="132130655400000000" Dst="0" />
<file name="links_32.jpg" server="192.168.0.201/wangsteak/" local="132157832977208054" remote="132130655400000000" Dst="0" />
<file name="links_35.jpg" server="192.168.0.201/wangsteak/" local="132157832979138247" remote="132130655400000000" Dst="0" />
<file name="links_37.jpg" server="192.168.0.201/wangsteak/" local="132157832979198253" remote="132130655400000000" Dst="0" />
<file name="links_42.jpg" server="192.168.0.201/wangsteak/" local="132157832979288262" remote="132130655400000000" Dst="0" />
<file name="links_39.jpg" server="192.168.0.201/wangsteak/" local="132157832981188452" remote="132130655400000000" Dst="0" />
<file name="links_44.jpg" server="192.168.0.201/wangsteak/" local="132157832981338467" remote="132130655400000000" Dst="0" />
<file name="logo-mobile.png" server="192.168.0.201/wangsteak/" local="132157832981428476" remote="132130655400000000" Dst="0" />
<file name="logo.png" server="192.168.0.201/wangsteak/" local="132157832981468480" remote="132130655400000000" Dst="0" />
<file name="member-01.jpg" server="192.168.0.201/wangsteak/" local="132157832981628496" remote="132130655400000000" Dst="0" />
<file name="member-icon-01.png" server="192.168.0.201/wangsteak/" local="132157832981698503" remote="132130655400000000" Dst="0" />
<file name="member-icon-02.png" server="192.168.0.201/wangsteak/" local="132157832981778511" remote="132130655400000000" Dst="0" />
<file name="member-banner.jpg" server="192.168.0.201/wangsteak/" local="132157832981798513" remote="132130655400000000" Dst="0" />
<file name="member-icon-03.png" server="192.168.0.201/wangsteak/" local="132157832981858519" remote="132130655400000000" Dst="0" />
<file name="menu-02-01.jpg" server="192.168.0.201/wangsteak/" local="132157832981998533" remote="132130655400000000" Dst="0" />
<file name="menu-02-02.jpg" server="192.168.0.201/wangsteak/" local="132157832982018535" remote="132130655400000000" Dst="0" />
<file name="menu-02-03.jpg" server="192.168.0.201/wangsteak/" local="132157832982118545" remote="132130655400000000" Dst="0" />
<file name="menu-03-01.jpg" server="192.168.0.201/wangsteak/" local="132157832982288562" remote="132130655400000000" Dst="0" />
<file name="menu-03-011.jpg" server="192.168.0.201/wangsteak/" local="132157832982658599" remote="132130655400000000" Dst="0" />
<file name="menu-03-010.jpg" server="192.168.0.201/wangsteak/" local="132157832984388772" remote="132130655400000000" Dst="0" />
<file name="menu-02-04.jpg" server="192.168.0.201/wangsteak/" local="132157832984468780" remote="132130655400000000" Dst="0" />
<file name="menu-03-012.jpg" server="192.168.0.201/wangsteak/" local="132157832986468980" remote="132130655400000000" Dst="0" />
<file name="menu-03-03.jpg" server="192.168.0.201/wangsteak/" local="132157832986779011" remote="132130655400000000" Dst="0" />
<file name="menu-03-013.jpg" server="192.168.0.201/wangsteak/" local="132157832986809014" remote="132130655400000000" Dst="0" />
<file name="menu-03-02.jpg" server="192.168.0.201/wangsteak/" local="132157832986869020" remote="132130655400000000" Dst="0" />
<file name="menu-03-04.jpg" server="192.168.0.201/wangsteak/" local="132157832986989032" remote="132130655400000000" Dst="0" />
<file name="menu-03-05.jpg" server="192.168.0.201/wangsteak/" local="132157832987019035" remote="132130655400000000" Dst="0" />
<file name="menu-03-07.jpg" server="192.168.0.201/wangsteak/" local="132157832987199053" remote="132130655400000000" Dst="0" />
<file name="menu-03-08.jpg" server="192.168.0.201/wangsteak/" local="132157832987239057" remote="132130655400000000" Dst="0" />
<file name="menu-03-06.jpg" server="192.168.0.201/wangsteak/" local="132157832989139247" remote="132130655400000000" Dst="0" />
<file name="menu-03-09.jpg" server="192.168.0.201/wangsteak/" local="132157832989759309" remote="132130655400000000" Dst="0" />
<file name="menu-03-10.jpg" server="192.168.0.201/wangsteak/" local="132157832989789312" remote="132130655400000000" Dst="0" />
<file name="menu-banner.jpg" server="192.168.0.201/wangsteak/" local="132157832991479481" remote="132130655400000000" Dst="0" />
<file name="menu-bg.jpg" server="192.168.0.201/wangsteak/" local="132157832992019535" remote="132130655400000000" Dst="0" />
<file name="menu-box2-list -1.jpg" server="192.168.0.201/wangsteak/" local="132157832992059539" remote="132130655400000000" Dst="0" />
<file name="menu-box2-list-1.jpg" server="192.168.0.201/wangsteak/" local="132157832992489582" remote="132130655400000000" Dst="0" />
<file name="menu-box2-list-2.jpg" server="192.168.0.201/wangsteak/" local="132157832993919725" remote="132130655400000000" Dst="0" />
<file name="menu-box2-list -2.jpg" server="192.168.0.201/wangsteak/" local="132157832994019735" remote="132130655400000000" Dst="0" />
<file name="menu-box2-list-4.jpg" server="192.168.0.201/wangsteak/" local="132157832994309764" remote="132130655400000000" Dst="0" />
<file name="menu-box2-list -3.jpg" server="192.168.0.201/wangsteak/" local="132157832994399773" remote="132130655400000000" Dst="0" />
<file name="menu-pic_03.jpg" server="192.168.0.201/wangsteak/" local="132157832994719805" remote="132130655400000000" Dst="0" />
<file name="menu-pic_04.jpg" server="192.168.0.201/wangsteak/" local="132157832996469980" remote="132130655400000000" Dst="0" />
<file name="menu-box2-list-3.jpg" server="192.168.0.201/wangsteak/" local="132157832996489982" remote="132130655400000000" Dst="0" />
<file name="menu-pic_02.jpg" server="192.168.0.201/wangsteak/" local="132157832996690002" remote="132130655400000000" Dst="0" />
<file name="menu-pic_05.jpg" server="192.168.0.201/wangsteak/" local="132157832996770010" remote="132130655400000000" Dst="0" />
<file name="menu-pic_06.jpg" server="192.168.0.201/wangsteak/" local="132157832998790212" remote="132130655400000000" Dst="0" />
<file name="menu-pic_08.jpg" server="192.168.0.201/wangsteak/" local="132157832998970230" remote="132130655400000000" Dst="0" />
<file name="menu-pic_09.jpg" server="192.168.0.201/wangsteak/" local="132157832999120245" remote="132130655400000000" Dst="0" />
<file name="menu-pic_12.jpg" server="192.168.0.201/wangsteak/" local="132157832999420275" remote="132130655400000000" Dst="0" />
<file name="menu-pic_10.jpg" server="192.168.0.201/wangsteak/" local="132157833001310464" remote="132130655400000000" Dst="0" />
<file name="menu-pic_11.jpg" server="192.168.0.201/wangsteak/" local="132157833001390472" remote="132130655400000000" Dst="0" />
<file name="menu-sw-01.jpg" server="192.168.0.201/wangsteak/" local="132157833001580491" remote="132130655400000000" Dst="0" />
<file name="menu-sw-02.jpg" server="192.168.0.201/wangsteak/" local="132157833001750508" remote="132130655400000000" Dst="0" />
<file name="qrcode.jpg" server="192.168.0.201/wangsteak/" local="132157833001960529" remote="132130655400000000" Dst="0" />
<file name="slogo.png" server="192.168.0.201/wangsteak/" local="132157833003780711" remote="132130655400000000" Dst="0" />
<file name="menu-sw-03 - 複製.jpg" server="192.168.0.201/wangsteak/" local="132157833003810714" remote="132130655400000000" Dst="0" />
<file name="menu-sw-03.jpg" server="192.168.0.201/wangsteak/" local="132157833003840717" remote="132130655400000000" Dst="0" />
<file name="steak_original.jpg" server="192.168.0.201/wangsteak/" local="132157833004070740" remote="132130655400000000" Dst="0" />
<file name="store-banner.jpg" server="192.168.0.201/wangsteak/" local="132157833004330766" remote="132130655400000000" Dst="0" />
<file name="store-icon.png" server="192.168.0.201/wangsteak/" local="132157833005850918" remote="132130655400000000" Dst="0" />
<file name="steak_onion.jpg" server="192.168.0.201/wangsteak/" local="132157833006020935" remote="132130655400000000" Dst="0" />
<file name="steak_source.jpg" server="192.168.0.201/wangsteak/" local="132157833006090942" remote="132130655400000000" Dst="0" />
<file name="store-map.jpg" server="192.168.0.201/wangsteak/" local="132157833006250958" remote="132130655400000000" Dst="0" />
<file name="store-map-icon.png" server="192.168.0.201/wangsteak/" local="132157833008101143" remote="132130655400000000" Dst="0" />
<file name="voucher-banner.jpg" server="192.168.0.201/wangsteak/" local="132157833008251158" remote="132130655400000000" Dst="0" />
<file name="wowprime-logo.png" server="192.168.0.201/wangsteak/" local="132157833008301163" remote="132130655400000000" Dst="0" />
<file name="ws_fb.jpg" server="192.168.0.201/wangsteak/" local="132157833008501183" remote="132130655400000000" Dst="0" />
</dwsync>